  {
  "apiName" : "SimpleDealAccounts",
  "label" : "SimpleDealAccounts",
  "dbTable" : "simple_deal_accounts",
  "objectType" : "STANDARD",
  "dataStore" : "POSTGRES",
  "deleted" : false,
  "enableAuditLog" : true,
  "schemaUpdatable" : false,
  "fields" : [ {
    "dbName" : "id",
    "hidden" : false,
    "deleted" : false,
    "idField" : true,
    "indexed" : true,
    "dataType" : "UUID",
    "required" : true,
    "sortable" : false,
    "fieldName" : "Id",
    "fieldType" : "COLUMN",
    "groupable" : false,
    "updatable" : false,
    "fieldLabel" : "Id",
    "filterable" : true,
    "foreignKey" : false,
    "insertable" : false,
    "displayOrder" : 0,
    "foreignKeyInfo" : null,
    "schemaUpdatable" : false,
    "displayField" : false
  },{
    "dbName" : "deal_id",
    "hidden" : false,
    "deleted" : false,
    "idField" : false,
    "indexed" : false,
    "dataType" : "UUID",
    "required" : true,
    "sortable" : true,
    "fieldName" : "DealId",
    "fieldType" : "COLUMN",
    "groupable" : true,
    "updatable" : true,
    "fieldLabel" : "Deal Id",
    "filterable" : true,
    "foreignKey" : true,
    "insertable" : true,
    "displayOrder" : 10,
    "foreignKeyInfo" : {
      "primaryKeyName" : "Id",
      "parentObjectName" : "SimpleDeal",
      "primaryKeyDbName" : "id",
      "parentObjectDbName" : "simple_deal"
    },
    "schemaUpdatable" : false,
    "displayField" : false
  }, {
    "dbName" : "account_id",
    "hidden" : false,
    "deleted" : false,
    "idField" : false,
    "indexed" : false,
    "dataType" : "UUID",
    "required" : true,
    "sortable" : true,
    "fieldName" : "AccountId",
    "fieldType" : "COLUMN",
    "groupable" : true,
    "updatable" : true,
    "fieldLabel" : "Account Id",
    "filterable" : true,
    "foreignKey" : true,
    "insertable" : true,
    "displayOrder" : 10,
    "foreignKeyInfo" : {
      "primaryKeyName" : "Id",
      "parentObjectName" : "Account",
      "primaryKeyDbName" : "id",
      "parentObjectDbName" : "account"
    },
    "schemaUpdatable" : false,
    "displayField" : false
  },
   {
    "dbName" : "org_id",
    "hidden" : false,
    "deleted" : false,
    "idField" : false,
    "indexed" : true,
    "dataType" : "UUID",
    "required" : true,
    "sortable" : true,
    "fieldName" : "OrgId",
    "fieldType" : "COLUMN",
    "groupable" : true,
    "updatable" : true,
    "fieldLabel" : "Organization",
    "filterable" : true,
    "foreignKey" : true,
    "insertable" : true,
    "displayOrder" : 2,
    "foreignKeyInfo" : {
      "primaryKeyName" : "Id",
      "parentObjectName" : "Organization",
      "primaryKeyDbName" : "id",
      "parentObjectDbName" : "organization"
    },
    "schemaUpdatable" : false,
    "displayField" : false
  },
  {
    "dbName" : "created_date",
    "format" : null,
    "hidden" : false,
    "deleted" : false,
    "idField" : false,
    "indexed" : true,
    "dataType" : "DATETIME",
    "required" : true,
    "sortable" : true,
    "fieldName" : "CreatedDate",
    "fieldType" : "COLUMN",
    "groupable" : false,
    "updatable" : false,
    "fieldLabel" : "Created Date",
    "filterable" : true,
    "foreignKey" : false,
    "insertable" : false,
    "timezoneId" : null,
    "displayOrder" : 96,
    "foreignKeyInfo" : null,
    "schemaUpdatable" : false,
    "displayField" : false
  }, {
    "dbName" : "modified_date",
    "format" : null,
    "hidden" : false,
    "deleted" : false,
    "idField" : false,
    "indexed" : true,
    "dataType" : "DATETIME",
    "required" : true,
    "sortable" : true,
    "fieldName" : "ModifiedDate",
    "fieldType" : "COLUMN",
    "groupable" : false,
    "updatable" : false,
    "fieldLabel" : "Modified Date",
    "filterable" : true,
    "foreignKey" : false,
    "insertable" : false,
    "timezoneId" : null,
    "displayOrder" : 97,
    "foreignKeyInfo" : null,
    "schemaUpdatable" : false,
    "displayField" : false
  }, {
    "dbName" : "created_by",
    "hidden" : false,
    "deleted" : false,
    "idField" : false,
    "indexed" : true,
    "dataType" : "UUID",
    "required" : true,
    "sortable" : true,
    "fieldName" : "CreatedBy",
    "fieldType" : "COLUMN",
    "groupable" : true,
    "updatable" : false,
    "fieldLabel" : "Created By",
    "filterable" : true,
    "foreignKey" : true,
    "insertable" : false,
    "displayOrder" : 98,
    "foreignKeyInfo" : {
      "primaryKeyName" : "Id",
      "parentObjectName" : "User",
      "primaryKeyDbName" : "id",
      "parentObjectDbName" : "tenant_user"
    },
    "schemaUpdatable" : false,
    "displayField" : false
  }, {
    "dbName" : "modified_by",
    "hidden" : false,
    "deleted" : false,
    "idField" : false,
    "indexed" : true,
    "dataType" : "UUID",
    "required" : true,
    "sortable" : true,
    "fieldName" : "ModifiedBy",
    "fieldType" : "COLUMN",
    "groupable" : true,
    "updatable" : false,
    "fieldLabel" : "Modified By",
    "filterable" : true,
    "foreignKey" : true,
    "insertable" : false,
    "displayOrder" : 99,
    "foreignKeyInfo" : {
      "primaryKeyName" : "Id",
      "parentObjectName" : "User",
      "primaryKeyDbName" : "id",
      "parentObjectDbName" : "tenant_user"
    },
    "schemaUpdatable" : false,
    "displayField" : false
  }
   ]
}